enigmabox/EnigmaBox.py
enigmabox/__init__.py
enigmabox-1.1.0.dist-info/LICENSE
enigmabox-1.1.0.dist-info/METADATA
enigmabox-1.1.0.dist-info/WHEEL
enigmabox-1.1.0.dist-info/top_level.txt
enigmabox-1.1.0.dist-info/RECORD
