Metadata-Version: 2.2
Name: enigmabox
Version: 1.1.0
Summary: EnigmaBox  is a Python library for secure text encryption and decryption using AES-256  and Argon2id . It combines industry-standard cryptographic algorithms with a simple, intuitive interface, making it easy to protect sensitive data with strong encryption. Perfect for developers who need robust security without complexity.
Requires-Python: >=3.6
License-File: LICENSE
Requires-Dist: cryptography
Requires-Dist: argon2-cffi
Dynamic: requires-python
